aki/__init__.py
aki/cli.py
python_aki-0.1.0.dist-info/entry_points.txt
python_aki-0.1.0.dist-info/LICENSE.md
python_aki-0.1.0.dist-info/METADATA
python_aki-0.1.0.dist-info/WHEEL
python_aki-0.1.0.dist-info/RECORD
